convert_case_py/Case.py
convert_case_py/__init__.py
convert_case_py-0.0.2.dist-info/METADATA
convert_case_py-0.0.2.dist-info/WHEEL
convert_case_py-0.0.2.dist-info/top_level.txt
convert_case_py-0.0.2.dist-info/RECORD
