Metadata-Version: 2.1
Name: convert-case-py
Version: 0.0.2
Summary: Library to convert dict in different case
Home-page: https://bitbucket.org/informaticaljd
Author: Juan José Macanás Beteta
Author-email: juanjo.macanas@gmail.com
License: MIT
Platform: UNKNOWN
Classifier: Natural Language :: English
Classifier: Operating System :: Microsoft :: Windows
Classifier: Programming Language :: Python
Classifier: Programming Language :: Python :: 3
Classifier: Programming Language :: Python :: 3.7
Classifier: Programming Language :: Python :: 3.8
Classifier: Programming Language :: Python :: 3.9
Classifier: Programming Language :: Python :: 3.10
Requires-Python: >=3.7.0
